noknow/__init__.py
noknow/core.py
noknow/utils/__init__.py
noknow/utils/convert.py
noknow/utils/crypto.py
noknow-0.2.0.dist-info/LICENSE
noknow-0.2.0.dist-info/LICENSE.txt
noknow-0.2.0.dist-info/METADATA
noknow-0.2.0.dist-info/WHEEL
noknow-0.2.0.dist-info/top_level.txt
noknow-0.2.0.dist-info/RECORD
