Metadata-Version: 2.1
Name: noknow
Version: 0.2.0
Summary: Non-Interactive Zero-Knowledge Proof Implementation in Pure Python
Home-page: https://github.com/GoodiesHQ/noknow-python/
Author: Austin Archer
Author-email: aarcher73k@gmail.com
License: UNKNOWN
Platform: UNKNOWN
Classifier: License :: OSI Approved :: MIT License
Classifier: Topic :: Security :: Cryptography
Requires-Dist: ecpy
